[ {
  "name" : "Actual",
  "dataType" : "string",
  "hasIndex" : false,
  "unique" : false,
  "primarykey" : false,
  "namefield" : false,
  "nullable" : true,
  "custom" : true,
  "createable" : true,
  "updateable" : true,
  "audit" : false,
  "customizable" : false,
  "fieldLength" : 40,
  "fieldOrder" : 3,
  "fieldProperties" : {
    "autoGenerated" : "false"
  },
  "etag" : "a350c3d0-a8c4-460e-b21d-125cfee41918",
  "isExtended" : false
}, {
  "name" : "CreatedBy",
  "dataType" : "string",
  "hasIndex" : false,
  "unique" : false,
  "primarykey" : false,
  "namefield" : false,
  "nullable" : true,
  "custom" : true,
  "createable" : true,
  "updateable" : true,
  "audit" : false,
  "customizable" : false,
  "fieldLength" : 32,
  "fieldOrder" : 5,
  "fieldProperties" : {
    "standard" : "true",
    "autoGenerated" : "false",
    "isUpdateTimeStampField" : "false",
    "isSoftDeleteField" : "false"
  },
  "etag" : "52b32215-f1bc-4c2d-80eb-0e58832246a6",
  "isExtended" : false
}, {
  "name" : "CreatedDateTime",
  "dataType" : "date",
  "hasIndex" : false,
  "unique" : false,
  "primarykey" : false,
  "namefield" : false,
  "nullable" : false,
  "custom" : true,
  "createable" : false,
  "updateable" : true,
  "audit" : false,
  "customizable" : false,
  "fieldLength" : 32,
  "fieldOrder" : 7,
  "fieldProperties" : {
    "standard" : "true",
    "autoGenerated" : "false",
    "isUpdateTimeStampField" : "false",
    "isSoftDeleteField" : "false"
  },
  "etag" : "56f239c2-70cf-4d0f-a853-842a4f68fa80",
  "isExtended" : false
}, {
  "name" : "Forecasted",
  "dataType" : "string",
  "hasIndex" : false,
  "unique" : false,
  "primarykey" : false,
  "namefield" : false,
  "nullable" : true,
  "custom" : true,
  "createable" : true,
  "updateable" : true,
  "audit" : false,
  "customizable" : false,
  "fieldLength" : 40,
  "fieldOrder" : 2,
  "fieldProperties" : {
    "autoGenerated" : "false"
  },
  "etag" : "ef121220-5064-49ba-939c-851ec3837a86",
  "isExtended" : false
}, {
  "name" : "LastUpdatedBy",
  "dataType" : "string",
  "hasIndex" : false,
  "unique" : false,
  "primarykey" : false,
  "namefield" : false,
  "nullable" : true,
  "custom" : true,
  "createable" : true,
  "updateable" : true,
  "audit" : false,
  "customizable" : false,
  "fieldLength" : 32,
  "fieldOrder" : 6,
  "fieldProperties" : {
    "standard" : "true",
    "autoGenerated" : "false",
    "isUpdateTimeStampField" : "false",
    "isSoftDeleteField" : "false"
  },
  "etag" : "a5e1718a-5681-4ee8-8684-b0d9c5d52e09",
  "isExtended" : false
}, {
  "name" : "LastUpdatedDateTime",
  "dataType" : "date",
  "hasIndex" : false,
  "unique" : false,
  "primarykey" : false,
  "namefield" : false,
  "nullable" : false,
  "custom" : true,
  "createable" : false,
  "updateable" : true,
  "audit" : false,
  "customizable" : false,
  "fieldLength" : 32,
  "fieldOrder" : 8,
  "fieldProperties" : {
    "standard" : "true",
    "autoGenerated" : "false",
    "isUpdateTimeStampField" : "true",
    "isSoftDeleteField" : "false",
    "timeStampFieldFormat" : "yyyy-MM-dd'T'HH:mm:ss.SSS"
  },
  "etag" : "de32c7e3-2227-4b26-baf6-729b4d2a5ad4",
  "isExtended" : false
}, {
  "name" : "ProductLine",
  "dataType" : "string",
  "hasIndex" : false,
  "unique" : true,
  "primarykey" : true,
  "namefield" : false,
  "nullable" : false,
  "custom" : true,
  "createable" : true,
  "updateable" : true,
  "audit" : false,
  "customizable" : false,
  "fieldLength" : 40,
  "fieldOrder" : 1,
  "fieldProperties" : {
    "autoGenerated" : "false"
  },
  "etag" : "e9abde4a-8143-4ec2-b6d8-76744f584316",
  "isExtended" : false
}, {
  "name" : "SoftDeleteFlag",
  "dataType" : "boolean",
  "hasIndex" : false,
  "unique" : false,
  "primarykey" : false,
  "namefield" : false,
  "nullable" : true,
  "custom" : true,
  "createable" : false,
  "updateable" : true,
  "audit" : false,
  "customizable" : false,
  "fieldLength" : 1,
  "fieldOrder" : 9,
  "fieldProperties" : {
    "standard" : "true",
    "autoGenerated" : "false",
    "isUpdateTimeStampField" : "false",
    "isSoftDeleteField" : "true"
  },
  "etag" : "97902d49-db15-4006-bf1c-f4b2147ba163",
  "isExtended" : false
}, {
  "name" : "Variance",
  "dataType" : "string",
  "hasIndex" : false,
  "unique" : false,
  "primarykey" : false,
  "namefield" : false,
  "nullable" : true,
  "custom" : true,
  "createable" : true,
  "updateable" : true,
  "audit" : false,
  "customizable" : false,
  "fieldLength" : 40,
  "fieldOrder" : 4,
  "fieldProperties" : {
    "autoGenerated" : "false"
  },
  "etag" : "5fd97e16-fa46-4265-892b-edd5ea12de96",
  "isExtended" : false
} ]